fusionflow/__init__.py
fusionflow/__main__.py
fusionflow/ast_nodes.py
fusionflow/backend_adapters.py
fusionflow/interpreter.py
fusionflow/ir_export.py
fusionflow/lexer.py
fusionflow/merge_algorithm.py
fusionflow/parser.py
fusionflow/runtime.py
fusionflow/tokens.py
fusionflow/upeg.py
fusionflow-0.3.0.dist-info/licenses/LICENSE
fusionflow-0.3.0.dist-info/METADATA
fusionflow-0.3.0.dist-info/WHEEL
fusionflow-0.3.0.dist-info/entry_points.txt
fusionflow-0.3.0.dist-info/top_level.txt
fusionflow-0.3.0.dist-info/RECORD
