Metadata-Version: 2.4
Name: fusionflow
Version: 0.3.0
Summary: A temporal ML pipeline DSL with first-class branching
Author: FusionFlow Contributors
License: MIT
Project-URL: Homepage, https://github.com/Dinesh0401/fusionflow
Project-URL: Repository, https://github.com/Dinesh0401/fusionflow
Keywords: ml,pipeline,dsl,temporal,branching
Classifier: Development Status :: 3 - Alpha
Classifier: Intended Audience :: Developers
Classifier: License :: OSI Approved :: MIT License
Classifier: Programming Language :: Python :: 3
Classifier: Programming Language :: Python :: 3.8
Classifier: Programming Language :: Python :: 3.9
Classifier: Programming Language :: Python :: 3.10
Classifier: Programming Language :: Python :: 3.11
Requires-Python: >=3.8
License-File: LICENSE
Requires-Dist: pandas>=1.3.0
Requires-Dist: scikit-learn>=1.0.0
Requires-Dist: numpy>=1.20.0
Provides-Extra: dev
Requires-Dist: pytest>=7.0.0; extra == "dev"
Requires-Dist: black>=22.0.0; extra == "dev"
Requires-Dist: mypy>=0.950; extra == "dev"
Dynamic: license-file
